awx_exporter/__init__.py
awx_exporter/__main__.py
awx_exporter/awx_exporter.py
awx_exporter/connection.py
awx_exporter/exporter.py
awx_exporter/utils.py
awx_exporter-0.2.dist-info/LICENSE
awx_exporter-0.2.dist-info/METADATA
awx_exporter-0.2.dist-info/WHEEL
awx_exporter-0.2.dist-info/entry_points.txt
awx_exporter-0.2.dist-info/top_level.txt
awx_exporter-0.2.dist-info/RECORD
