Metadata-Version: 2.1
Name: awx-exporter
Version: 0.2
Summary: cli tool to create a portable/workstation compatible version of awx/tower inventories
Home-page: https://github.com/np-at/awx_exporter
Author: np-at
Author-email: 
License: GPL3
Platform: UNKNOWN
Requires-Python: >=3.5
Requires-Dist: PyYAML
Requires-Dist: requests
